libreary/__init__.py
libreary/adapter_manager.py
libreary/config_parser.py
libreary/exceptions.py
libreary/ingester.py
libreary/libreary.py
libreary/scheduler.py
libreary/version.py
libreary/adapters/BaseAdapter.py
libreary/adapters/__init__.py
libreary/adapters/drive.py
libreary/adapters/local.py
libreary/adapters/s3.py
libreary/metadata/__init__.py
libreary/metadata/base.py
libreary/metadata/base_metadata_manager.py
libreary/metadata/sqlite3.py
libreary-0.0.3.1.dist-info/LICENSE
libreary-0.0.3.1.dist-info/METADATA
libreary-0.0.3.1.dist-info/WHEEL
libreary-0.0.3.1.dist-info/top_level.txt
libreary-0.0.3.1.dist-info/RECORD
