Metadata-Version: 2.1
Name: libreary
Version: 0.0.3.1
Summary: Distributed Digital Object Archive System
Home-page: https://github.com/LIBREary/libre-ary
Author: Ben Glick
Author-email: glick@glick.cloud
License: Apache 2.0
Download-URL: https://github.com/LIBREary/libre-ary#0.0.3.1
Keywords: Archive,Distributed Systems
Platform: UNKNOWN
Classifier: Development Status :: 3 - Alpha
Classifier: Intended Audience :: Developers
Classifier: License :: OSI Approved :: Apache Software License
Classifier: Programming Language :: Python :: 3.5
Classifier: Programming Language :: Python :: 3.6
Requires-Dist: boto3 (==1.11.1)
Requires-Dist: botocore (==1.14.1)
Requires-Dist: google-api-python-client (==1.7.11)
Requires-Dist: google-auth (==1.10.0)
Requires-Dist: google-auth-httplib2 (==0.0.3)
Requires-Dist: google-auth-oauthlib (==0.4.1)
Requires-Dist: flake8
Requires-Dist: pytest
Requires-Dist: python-crontab
